gym_cartpole_swingup/__init__.py
gym_cartpole_swingup/envs/__init__.py
gym_cartpole_swingup/envs/cartpole_swingup.py
gym_cartpole_swingup/envs/torch_cartpole_swingup.py
gym_cartpole_swingup-0.1.4.dist-info/LICENSE
gym_cartpole_swingup-0.1.4.dist-info/WHEEL
gym_cartpole_swingup-0.1.4.dist-info/METADATA
gym_cartpole_swingup-0.1.4.dist-info/RECORD
