Metadata-Version: 2.1
Name: gym-cartpole-swingup
Version: 0.1.4
Summary: A simple, continuous-control environment for OpenAI Gym
Home-page: https://github.com/angelolovatto/gym-cartpole-swingup
License: GNU General Public License v3.0
Author: Ângelo Gregório Lovatto
Author-email: angelolovatto@gmail.com
Requires-Python: >=3.7
Classifier: Development Status :: 2 - Pre-Alpha
Classifier: Intended Audience :: Developers
Classifier: License :: Other/Proprietary License
Classifier: Natural Language :: English
Classifier: Programming Language :: Python :: 3
Classifier: Programming Language :: Python :: 3.7
Classifier: Programming Language :: Python :: 3.8
Classifier: Programming Language :: Python :: 3.9
Requires-Dist: gym (>=0.18.0,<0.19.0)
Requires-Dist: poetry-version (>=0.1.5,<0.2.0)
Project-URL: Repository, https://github.com/angelolovatto/gym-cartpole-swingup
